oct_turrets/__init__.py
oct_turrets/base.py
oct_turrets/cannon.py
oct_turrets/config.py
oct_turrets/exceptions.py
oct_turrets/start_turret.py
oct_turrets/tools.py
oct_turrets/turret.py
oct_turrets/utils.py
oct_turrets-0.2.8.dist-info/DESCRIPTION.rst
oct_turrets-0.2.8.dist-info/LICENSE.txt
oct_turrets-0.2.8.dist-info/METADATA
oct_turrets-0.2.8.dist-info/RECORD
oct_turrets-0.2.8.dist-info/WHEEL
oct_turrets-0.2.8.dist-info/entry_points.txt
oct_turrets-0.2.8.dist-info/metadata.json
oct_turrets-0.2.8.dist-info/top_level.txt
